stage0_py_utils/__init__.py
stage0_py_utils/server.py
stage0_py_utils/agents/__init__.py
stage0_py_utils/agents/bot_agent.py
stage0_py_utils/agents/config_agent.py
stage0_py_utils/agents/conversation_agent.py
stage0_py_utils/agents/echo_agent.py
stage0_py_utils/config/__init__.py
stage0_py_utils/config/config.py
stage0_py_utils/echo/__init__.py
stage0_py_utils/echo/agent.py
stage0_py_utils/echo/discord_bot.py
stage0_py_utils/echo/echo.py
stage0_py_utils/echo/llm_handler.py
stage0_py_utils/echo/message.py
stage0_py_utils/echo/mock_llm_client.py
stage0_py_utils/echo/ollama_llm_client.py
stage0_py_utils/echo_utils/__init__.py
stage0_py_utils/echo_utils/breadcrumb.py
stage0_py_utils/echo_utils/token.py
stage0_py_utils/evaluator/__init__.py
stage0_py_utils/evaluator/evaluator.py
stage0_py_utils/evaluator/loader.py
stage0_py_utils/flask_utils/__init__.py
stage0_py_utils/flask_utils/breadcrumb.py
stage0_py_utils/flask_utils/ejson_encoder.py
stage0_py_utils/flask_utils/token.py
stage0_py_utils/mongo_utils/__init__.py
stage0_py_utils/mongo_utils/encode_properties.py
stage0_py_utils/mongo_utils/mongo_io.py
stage0_py_utils/routes/__init__.py
stage0_py_utils/routes/bot_routes.py
stage0_py_utils/routes/config_routes.py
stage0_py_utils/routes/conversation_routes.py
stage0_py_utils/routes/echo_routes.py
stage0_py_utils/services/__init__.py
stage0_py_utils/services/bot_services.py
stage0_py_utils/services/conversation_services.py
stage0_py_utils-0.2.15.dist-info/licenses/LICENSE
stage0_py_utils-0.2.15.dist-info/METADATA
stage0_py_utils-0.2.15.dist-info/WHEEL
stage0_py_utils-0.2.15.dist-info/top_level.txt
stage0_py_utils-0.2.15.dist-info/RECORD
