Metadata-Version: 2.4
Name: stage0_py_utils
Version: 0.2.15
Summary: A utility package for stage0 microservices
Author: Mike Storey
Author-email: Mike Storey <devs@agile-learning.institute>
License: MIT
Requires-Python: >=3.8
License-File: LICENSE
Requires-Dist: flask
Requires-Dist: pymongo
Requires-Dist: discord
Requires-Dist: ollama
Provides-Extra: dev
Requires-Dist: black; extra == "dev"
Requires-Dist: pytest; extra == "dev"
Requires-Dist: unittest; extra == "dev"
Dynamic: author
Dynamic: license-file
Dynamic: requires-python
